datatui/__init__.py
datatui/__main__.py
datatui/app.py
datatui/static/app.css
tests/__init__.py
tests/test_init.py
tests/test_state.py
datatui-0.0.2.dist-info/LICENSE
datatui-0.0.2.dist-info/METADATA
datatui-0.0.2.dist-info/WHEEL
datatui-0.0.2.dist-info/top_level.txt
datatui-0.0.2.dist-info/RECORD
