Metadata-Version: 2.1
Name: datatui
Version: 0.0.2
License-File: LICENSE
Requires-Dist: diskcache
Requires-Dist: textual
Requires-Dist: srsly
Requires-Dist: click
